AUTHORS.md
LICENSE
README.md
setup.cfg
setup.py
binsdpy/__init__.py
binsdpy/distance.py
binsdpy/similarity.py
binsdpy/utils.py
binsdpy.egg-info/PKG-INFO
binsdpy.egg-info/SOURCES.txt
binsdpy.egg-info/dependency_links.txt
binsdpy.egg-info/requires.txt
binsdpy.egg-info/top_level.txt