Metadata-Version: 2.1
Name: binsdpy
Version: 0.2.4
Summary: Python implementation of binary similarity and distance measures.
Home-page: https://github.com/mikulatomas/binsdpy
Author: Tomáš Mikula
Author-email: mail@tomasmikula.cz
License: MIT license
Keywords: binary similarity distance measure
Platform: UNKNOWN
Classifier: Development Status :: 2 - Pre-Alpha
Classifier: Intended Audience :: Science/Research
Classifier: Intended Audience :: Developers
Classifier: License :: OSI Approved :: MIT License
Classifier: Natural Language :: English
Classifier: Programming Language :: Python :: 3
Classifier: Programming Language :: Python :: 3.6
Classifier: Programming Language :: Python :: 3.7
Classifier: Programming Language :: Python :: 3.8
Classifier: Programming Language :: Python :: 3.9
Classifier: Programming Language :: Python :: 3.10
Requires-Python: >=3.6
Provides-Extra: test
License-File: LICENSE
License-File: AUTHORS.md
